sungrow_websocket/__init__.py
sungrow_websocket/version.py
sungrow_websocket-0.2.2.dist-info/LICENSE.txt
sungrow_websocket-0.2.2.dist-info/METADATA
sungrow_websocket-0.2.2.dist-info/WHEEL
sungrow_websocket-0.2.2.dist-info/entry_points.txt
sungrow_websocket-0.2.2.dist-info/top_level.txt
sungrow_websocket-0.2.2.dist-info/RECORD
