Metadata-Version: 2.1
Name: sungrow-websocket
Version: 0.2.2
Summary: Add a short description here!
Home-page: https://github.com/wallento/sungrow-websocket
Author: Stefan Wallentowitz
Author-email: stefan.wallentowitz@hm.edu
License: MIT
Requires-Python: >=3.9
License-File: LICENSE.txt
Requires-Dist: aiohttp
Requires-Dist: terminaltables
Requires-Dist: websockets
